{
  "id": "HC03189",
  "typ": "lagforslag",
  "titel": "Kriminalisierung von Jungfrulichkeitsuntersuchungen, Jungfrulichkeitszertifikaten und Jungfrulichkeitsoperationen.",
  "datum": "2025-06-17",
  "kalla": "Riksdagen",
  "kalla_url": "https://data.riksdagen.se/dokument/HC03189.html",
  "taggar": [
    "straffratt",
    "hedersrelaterat-vald",
    "kvinnoratt",
    "regeringen",
    "brottsbalken",
    "riksdagen"
  ],
  "html": "<p>In Schweden gibt es Jungfrlichkeitsuntersuchungen, Jungfrlichkeitszeugnisse und Eingriffe in die Geschlechtsorgane, sowohl innerhalb als auch außerhalb des Gesundheitswesens. Dies kann zu schwerwiegenden körperlichen und psychischen Folgen für die Betroffenen führen. Um den Schutz von Mädchen und Frauen, die in einem Ehrenkontext leben, zu stärken, schlägt die Regierung vor, die beiden neuen Straftatbestände „Jungfrlichkeitsuntersuchung“ und „Bescheinigung der sexuellen Jungfrlichkeit“ in den Strafgesetzbuches aufzunehmen und ein strafrechtlich sanktioniertes Verbot von „Eingriffen in die Geschlechtsorgane“ in das Gesetz (1982:316) über das Verbot der Genitalverstümmelung von Frauen aufzunehmen. Darüber hinaus wird vorgeschlagen, die Unterlassung der Anzeige oder Verhinderung von Zwangsehen und Kinderehen als Straftaten zu behandeln.</p><p>Die Vorschläge bedeuten, dass folgende Handlungen strafbar werden:</p><p>*   Die Untersuchung der weiblichen Geschlechtsorgane einer anderen Person mit dem Zweck, für sich selbst oder für eine andere Person zu beurteilen, ob die Person ein vaginales Geschlechtsverkehr hatte oder ob der Eindruck entsteht, dass die Person einen solchen hatte oder an vergleichbaren sexuellen Handlungen teilgenommen hat.\n*   Die schriftliche oder mündliche Bescheinigung, dass eine andere Person ein vaginales Geschlechtsverkehr hatte oder an vergleichbaren sexuellen Handlungen teilgenommen hat, oder dass dies nicht der Fall ist, unter Berücksichtigung der Beschaffenheit der weiblichen Geschlechtsorgane.\n*   Der Eingriff in die weiblichen Geschlechtsorgane einer anderen Person mit dem Zweck, den Eindruck zu erwecken, dass die Person keinen vaginalen Geschlechtsverkehr hatte oder nicht an vergleichbaren sexuellen Handlungen teilgenommen hat.\n*   Die Unterlassung der Anzeige oder Verhinderung von Zwangsehen und Kinderehen.</p>",
  "relevans": {
    "barn": 1,
    "kvinna": 2,
    "klimat": 1
  }
}