{
  "id": "HD03230",
  "typ": "lagforslag",
  "titel": "Kártérítés a fajok védelméből adódó tulajdonjogi korlátozások esetén.",
  "datum": "2026-04-08",
  "kalla": "Riksdagen",
  "kalla_url": "https://data.riksdagen.se/dokument/HD03230.html",
  "taggar": [
    "riksdagen"
  ],
  "html": "<p>A javaslat célja, hogy biztosítsa, hogy a tulajdonosok megfelelő kártérítést kapjanak, amikor a növény- és állatvédelemmel kapcsolatos szabályozások korlátozzák a meglévő földhasználatot. A környezetvédelmi törvényben foglaltak szerint, amely kártérítésre vonatkozik az állami beavatkozások esetén, például a bizonyos területhasználati korlátozások miatt, a javaslat szerint ez a szabályozás alkalmazandó abban az esetben is, ha a tulajdonosok jogainak korlátozása a fajvédelmi rendeletben foglalt védelmi előírások teljes vagy részleges elutasítása miatt következik be.</p><p>A javaslat értelmében a államnak lehetősége van visszakövetelni a kártérítést abban az esetben, ha a fajvédelem következtében bevezetett korlátozás megszűnik, vagy ha olyan intézkedéseket hajtanak végre, amelyek ellentétesek a kártérítés alapját képező döntéssel. Hasonló szabály vonatkozik a területhasználati korlátozásokra utaló döntésekre folyósított kártérítésekre is.</p><p>A törvényben a kártérítéshez való jog egyértelművé tételével feltételeket teremtünk annak, hogy az állam önkéntes megállapodást kössön a tulajdonosokkal, akik a fajvédelemmel kapcsolatos okokból kártérítésre jogosultak.</p><p>A törvénymódosítások a kormány által meghatározott naptól lépnek hatályba.</p><h3>Javaslat a parlament döntéséhez</h3><p>Prop. 2025/26:230</p><p>Kormányzati javaslat: A parlament elfogadja a kormány által javasolt törvényjavaslatot a környezetvédelmi törvény módosításáról. 3</p><p>Prop. 2025/26:230 2 Törvényjavaslat a környezetvédelmi törvény módosításáról</p><p>Ezúton rendelkezéseket fogadunk el a környezetvédelmi törvény tekintetében, részben a 31. fejezet 4., 5., 9. és 13. §-ainak szövegét módosítjuk, részben pedig egy új §-t vezetünk be, a 31. fejezet 15. a. §-át a következő szöveggel:</p><p>Jelenlegi szöveg Javasolt szöveg</p><ol><li>fejezet</li><li>§ 1</li></ol><p>A tulajdonosnak joga van kártérítéshez, amennyiben az egy ingatlanon lévő terület használatának jelentős nehézségeket okozó döntésről van szó, amennyiben a döntés a következőkre vonatkozik:</p><ol><li>a 7. fejezet 3. §-ában foglalt előírások az országos parkokkal,</li><li>a 7. fejezet 5., 6. vagy 9. §-ában foglalt előírások a természetvédelmi és kulturális rezervátumokkal kapcsolatban,</li><li>a 7. fejezet 11. § második bekezdésében foglalt engedély, amely külön feltételekkel kapcsolódik, vagy a 7. fejezet 11. § második bekezdésében foglalt engedély iránti kérelmet elutasítják, amennyiben az engedély egy 7. fejezet 11. § első bekezdés 1. pontja szerinti élőhelyvédelmi területre vonatkozik,</li><li>egy 7. fejezet 11. § első bekezdés 2. pontja szerinti élőhelyvédelmi terület létrehozása,</li><li>a 7. fejezet 22. §-ában foglalt előírások a védett vizekkel kapcsolatban,</li><li>a 7. fejezet 28a-29b. §-ai szerinti különleges területek védelme,</li><li>a 8. fejezet 1. vagy 2. §-a alapján kiadott előírások szerinti engedély iránti kérelmet elutasítják, vagy egy ilyen előírások szerinti engedély, amely külön feltételekkel kapcsolódik,</li></ol><ol><li>előírások</li></ol><p>vagy tilalmak</p><ol><li>előírások</li></ol><p>vagy tilalmak az 12. fejezet 6. § negyedik bekezdésében az 12. fejezet 6. § negyedik bekezdésében amelyek bizonyos tevékenységekre vonatkoznak, vagy amelyek bizonyos tevékenységekre vonatkoznak, vagy</p><ol><li>az 20. §-ban említett előírások</li><li>az 20. §</li></ol><p>harmadik bekezdés 1. pontjában említett harmadik bekezdés 1. pontjában említett a halászati törvényről (1993:787). a halászati törvényről (1993:787).</p><p>A 7. fejezet 3. §-ában foglalt előírás, amely korlátozza a medve, szarvasmarha, farkas, róka, hiéna, szarvas vagy sas vadászatának lehetőségét, nem jár kártérítéshez.</p><ol><li>§ 2</li></ol><p>Amennyiben a 4. § Amennyiben a 4. § első bekezdés 1., 2., 5., 6. vagy 8. első bekezdés 1., 2., 5., 6. vagy 9. pontja szerinti döntés pontja szerinti döntés előírja, hogy egy előírja, hogy egy bizonyos tevékenységhez vagy bizonyos tevékenységhez vagy művelethez engedély művelethez engedély szükséges, a kártérítés szükséges, a kártérítés csak akkor jár, ha csak akkor jár, ha 4 1 Utolsó módosítás: 2025:270.</p>",
  "tldr": "A kormány új szabályokat terjeszt elő, amelyek értelmében a földtulajdonosok pénzbeli kompenzációt kaphatnak, ha a védett állatok és növények miatt nehézségek merülnek fel a földjük használatában. A cél az, hogy egyértelműbbé tegyék, milyen jogok illetik meg azokat, akikre a természetvédelem miatt korlátozások érvényesülnek.",
  "lattlast": "<p>A kormány egy javaslatot terjesztett elő a környezetvédelmi törvény módosítására, amely a jogszabály, amely meghatározza, hogyan kell gondoskodnunk a természetről. A javaslat célja, hogy azoknak a személyeknek, akik földet vagy erdőt birtokolnak, kártérítéshez jussanak, amennyiben az állami szabályozások, amelyek a növény- és állatvédelemre vonatkoznak, megnehezítik a föld használatát oly módon, ahogy azt korábban tették.</p><p>Jelenleg is vannak szabályok a kártérítésre, ha az állam például természetvédelmi területeket vagy vízvédelmi területeket hoz létre. Az új javaslat azt is lehetővé teszi, hogy pénzügyi támogatást kaphassanak azok, akiknek az állam megtiltja bizonyos tevékenységek végzését a földjükön a fajvédelem miatt. A fajvédelem az a szabályrendszer, amelynek célja, hogy a védett állatok és növények ne sérüljenek.</p><p>A javaslat tartalmaz egy olyan rendelkezést is, amely szerint az állam visszakövetelheti a pénzt, ha a korlátozás a földtulajdonos számára megszűnik, vagy ha a földtulajdonos nem tartja be a meghatározott szabályokat. Ez a rendelkezés már létezik más típusú védett területek esetében is.</p><p>A módosítás célja, hogy az állam és a földtulajdonosok könnyebben tudjanak megállapodni, anélkül, hogy bírósági útra kényszerülnének. Ha a parlament megszavazza a javaslatot, az új szabályok akkor lépnek hatályba, amikor a kormány határozza meg.</p>",
  "relevans": {
    "glesbygd": 1,
    "klimat": 1
  }
}