{
  "id": "HD03253",
  "typ": "lagforslag",
  "titel": "Az EU bankcsomagja.",
  "datum": "2026-04-23",
  "kalla": "Riksdagen",
  "kalla_url": "https://data.riksdagen.se/dokument/HD03253.html",
  "taggar": [
    "riksdagen"
  ],
  "html": "<p>Az EU-s tőkekinálati direktíva előírásokat tartalmaz a bankok és a hitelintézetek, valamint a nagyon nagy értékpapír-vállalatok és bizonyos holdingtársaságok által végzett tevékenységekkel kapcsolatban. A javaslatban a törvényi módosításokról szóló javaslatokat tartalmazza, amelyek szükségesek ahhoz, hogy végrehajtsák azokat a módosításokat, amelyek a &quot;bankcsomag&quot; keretében történtek a tőkekinálati direktívában. A javaslatok többek között a következőket tartalmazzák:</p><ul><li>Engedélyköteles lesz azoknak a vállalatoknak, amelyek az Európai Gazdasági Együttműködési Térség (EGT) területén kívüli országokból származnak, és amelyek központi, banki szolgáltatásokat kívánnak egy svéd fiókból nyújtani.</li><li>A hitelintézetek vezetőségére vonatkozó alkalmassági követelmények a nagyon nagy értékpapír-vállalatokra és bizonyos holdingtársaságokra is vonatkoznak.</li><li>Bizonyos vállalatoknak kötelező előzetesen bejelenteniük új vezetői személyek adatait.</li><li>A vállalatoknak kötelező alkalmassági felülvizsgálatot végezniük bizonyos vezető beosztásban lévő személyek esetében.</li><li>Bizonyos tranzakciókra vonatkozó kérelmezési eljárásokat vezetnek be.</li><li>Bizonyos munkavállalókra és megbízottak számára kötelező a Finansinspektionen (Pénzügyi Felügyelet) által előírt időtartam.</li></ul><p>A törvénymódosítások 2026. július 1-jén lépnek hatályba, kivéve a különleges engedélykötelmekre és a különleges felügyeleti szabályozásokra vonatkozó módosításokat, amelyek az EGT területén kívüli országokból származó vállalatokra vonatkoznak, amelyek központi, banki szolgáltatásokat kívánnak egy svéd fiókból nyújtani, és amelyek 2027. január 11-én lépnek hatályba.</p><h3>Javaslat a parlament döntéseire vonatkozóan</h3><p>A kormány javaslatai:</p><ol><li>A parlament elfogadja a kormány által javasolt törvényjavaslatot a Finansinspektionen (finansfelügyeleti szervezet) egyes tisztviselőinek a más tevékenységre való átálláskor alkalmazandó korlátozásokról.</li><li>A parlament elfogadja a kormány által javasolt törvényjavaslatot a szociális biztonsági törvény módosításáról.</li><li>A parlament elfogadja a kormány által javasolt törvényjavaslatot a hitelinformációs törvény (1973:1173) módosításáról.</li><li>A parlament elfogadja a kormány által javasolt törvényjavaslatot a takarékbanki törvény (1987:619) módosításáról.</li><li>A parlament elfogadja a kormány által javasolt törvényjavaslatot a pénzügyi eszközökkel kapcsolatos kereskedelemmel foglalkozó törvény (1991:980) módosításáról.</li><li>A parlament elfogadja a kormány által javasolt törvényjavaslatot a külföldi fiókokról szóló törvény (1992:160) módosításáról.</li><li>A parlament elfogadja a kormány által javasolt törvényjavaslatot a zálogházakkal kapcsolatos törvény (1995:1000) módosításáról.</li><li>A parlament elfogadja a kormány által javasolt törvényjavaslatot a betétbiztosításról szóló törvény (1995:1571) módosításáról.</li><li>A parlament elfogadja a kormány által javasolt törvényjavaslatot a bizonyos pénzügyi tevékenységekről szóló törvény (1996:1006) módosításáról.</li><li>A parlament elfogadja a kormány által javasolt törvényjavaslatot a pénzügyi vállalkozásoknál alkalmazandó könyvelési valutaváltásról szóló törvény (2000:35) módosításáról.</li><li>A parlament elfogadja a kormány által javasolt törvényjavaslatot a banki és pénzügyi tevékenységről szóló törvény (2004:297) módosításáról.</li><li>A parlament elfogadja a kormány által javasolt törvényjavaslatot a banki és pénzügyi tevékenységről szóló törvény (2004:297) módosításáról.</li><li>A parlament elfogadja a kormány által javasolt törvényjavaslatot a értékpapírpiacról szóló törvény (2007:528) módosításáról.</li><li>A parlament elfogadja a kormány által javasolt törvényjavaslatot a közérdek és a titoktartásról szóló törvény (2009:400) módosításáról.</li><li>A parlament elfogadja a kormány által javasolt törvényjavaslatot a fizetési szolgáltatásokról szóló törvény (2010:751) módosításáról.</li><li>A parlament elfogadja a kormány által javasolt törvényjavaslatot az elektronikus pénzről szóló törvény (2011:755) módosításáról.</li><li>A parlament elfogadja a kormány által javasolt törvényjavaslatot az alternatív befektetési alapok kezelőiről szóló törvény (2013:561) módosításáról.</li><li>A parlament elfogadja a kormány által javasolt törvényjavaslatot a tőkepufferekről szóló törvény (2014:966) módosításáról.</li><li>A parlament elfogadja a kormány által javasolt törvényjavaslatot a hitintézetek és értékpapír-boltokra vonatkozó különleges felügyeletéről szóló törvény (2014:968) módosításáról.</li><li>A parlament elfogadja a kormány által javasolt törvényjavaslatot a feloldásról szóló törvény (2015:1016) módosításáról.</li><li>A parlament elfogadja a kormány által javasolt törvényjavaslatot a</li></ol><p>(2016:1306) számú törvényhez</p><p>kiegészítő</p><p>rendelkezésekkel,</p><p>amelyek</p><p>az</p><p>EU</p><p>piaci visszaélésekre</p><p>vonatkozó</p><p>rendeletét</p><p>kiegészítik.</p><p>8</p>",
  "relevans": {
    "b_finans": 3
  }
}