{
  "id": "hist-q543195",
  "typ": "historia",
  "titel": "Johan Henric Kellgren",
  "datum": "",
  "kalla": "Wikipedia",
  "kalla_url": "https://sv.wikipedia.org/wiki/Johan_Henric_Kellgren",
  "taggar": [
    "svensk-historia",
    "historisk-person",
    "frihetstiden"
  ],
  "html": "<p>Johan Henric Kellgren, urodzony 1 grudnia 1751 roku (zgodnie z aktem urodzenia) w parafii Floby w hrabstwie Skaraborg, zmarł 20 kwietnia 1795 roku w Sztokholmie. Był szwedzkim poetą, krytykiem, redaktorem czasopism oraz docentem od 1774 roku, specjalizującym się w literaturze łacińskiej.</p><p>== Biografia ==</p><p>Kellgren był synem proboszcza Jonas Kellgren z Floby w Westrogothlandii oraz jego żony, Christiny Elisabeth von Wulff. Dzięki bardzo dobrym ocenom uzyskanych na pięcioletnich studiach w gimnazjum w Skarze, w 1768 roku został wysłany do Królewskiej Akademii w Abo, gdzie w 1772 roku uzyskał tytuł magistra filozofii, a w 1774 roku otrzymał stanowisko docenta literatury. Kellgren był członkiem stowarzyszenia Aurorasällskapet w Abo, założonego w 1770 roku – fińskiej filii Utile Dulci – i anonimowo publikował w jego czasopiśmie kilka wierszy (1773–1776). Jego utwór &quot;Mina Löjen&quot; położył podwaliny pod jego sławę.</p><p>W 1777 roku przeniósł się do Sztokholmu, gdzie otrzymał stanowisko prywatnego nauczyciela u generał-lejtnanta, a później feldmarszałka Johana Augusta Meijerfeldta. Kolejne dowody swojego talentu poetyckiego prezentował w wierszach, które częściowo ukazały się w &quot;Samlaren&quot; autorstwa Carla Christoffera Gjörwella, a częściowo zostały nagrodzone przez Akademię Literatury i umieszczone w jej archiwach (&quot;En ynglings inträde i verlden&quot;). 29 października 1778 roku, wraz ze swoim przyjacielem, sekretarzem Carlem Peterem Lenngrenem, rozpoczął wydawanie gazety &quot;Stockholms-Posten&quot;, stając się pierwszym szwedzkim krytykiem teatralnym. Zyskał uznanie zarówno jako poeta, jak i jako błyskotliwy i ostry publicysta w duchu oświecenia.</p><p>Johan Henric Kellgren zwrócił na siebie uwagę króla Gustawa III, pisząc prolog do sztuki wystawionej w Drottningholm z okazji narodzin następcy tronu. Król przyznał mu rentę artystyczną, która została później zwiększona, gdy został mianowany królewskim bibliotekarzem, a następnie królewskim sekretarzem. W 1777 roku Kellgren został zarówno członkiem, jak i sekretarzem znanego towarzystwa literackiego Utile Dulci. W 1785 roku został wyznaczony wraz z Abrahamem Niclasem Clewbergiem na królewskiego cenzora. Podczas założenia Szwedzkiej Akademii w 1786 roku, został jednym z trzynastu członków wybranych przez króla i, dzięki losowaniu, został jej pierwszym dyrektorem. Został również przyjęty jako członek Królewskiej Akademii Muzycznej 18 kwietnia 1788 roku.</p><p>Kellgren miał słabe zdrowie od urodzenia, które pogorszyło się z powodu nadmiernego wysiłku i zmarł w Sztokholmie 20 kwietnia 1795 roku, będąc osobą stanu wolnego, na gruźlicę. W ciągu dwóch ostatnich lat życia poświęcił – w ogromnym cierpieniu – głównie porządkowaniu swoich dzieł.</p><p>Wśród utworów Kellgrena znajdują się liryczne utwory miłosne, takie jak &quot;Den nya skapelsen&quot;, oraz satyry, np. &quot;Man äger ej snille för det man är galen&quot; (1787) i &quot;Dumboms lefverne&quot; (1791), w których główną postacią jest Salig Dumbom. Uważa się, że Dumbom odnosi się do Pera Enboma. Kellgren napisał również przedmowę do &quot;Fredmans epistlar&quot; Bellmana, pomimo wcześniejszej niechęci wobec tego autora, którą wyraził w wierszu &quot;Mina löjen&quot; (1777).</p><p>Anacreoncie, gdzie jest Twoja chwała? Inny zrabował Twoją lirę, który, będąc w stanie upojenia, nauczył się rozweselać dwór Priapa. Kiedy w &quot;Minach&quot; żartobliwie mówił o &quot;szwedzkim Homerze&quot;, który &quot;chrapie w każdym wersie&quot;, miał na myśli Erika Skjöldebranda. W &quot;Wrogach Światła&quot; Kellgren argumentuje za trzymaniem się idei oświecenia, mimo że &quot;wszystko jest zepsute na południu&quot;, czyli że ludzie, w wyniku rewolucji francuskiej, zaczęli nadużywać tych idei. Filozoficznie był związany z Voltaire&#x27;em i francuskim rozumieniem sztuki. Kellgren wraz z Gustawem III napisał teksty do oper &quot;Gustaf Wasa&quot; (1786) i &quot;Gustaf Adolph oraz Ebba Brahe&quot; (1788). Rozpoczął również pierwszy wielki spór literacki w Szwecji z Thomasem Thorildem, który trwał od 1782 do 1792 roku. Podczas i po tym sporze jego gust się rozwijał, ponieważ zapoznał się z pismami Jensa Baggesena, Friedricha Gottlieba Klopstocka i zaczął interesować się literaturą innych krajów niż Francji, zwłaszcza nowo powstającą duńską. Johan Henric Kellgren został pochowany na cmentarzu przy kościele św. Jakuba, a w jego murze później umieszczono tablicę pamiątkową. Johan Tobias Sergel uwiecznił jego rysy twarzy na medalionie.</p><p>== Zobacz również == Mój błogosławiony brat Jean Hendrich Friedrich Gottlieb Klopstock Mathias Bjugg</p><p>== Bibliografia ==</p><p>=== Zebranie prac === Zebrane pisma. Wydawnictwa szwedzkich autorów publikowane przez Szwedzkie Towarzystwo Literackie, 0346-7864; 9. 1923-1981. Libris 114762. Część 1, Pisa pisma młodziecze. 1936-1937. Libris 114763. http://litteraturbanken.se/#!/forfattare/KellgrenJH/titlar/SamladeSkrifter1/info Część 2, Wiersze od początku publikacji &quot;Stockholms posten&quot; w roku 1778. 1938-1939. Libris 114764. http://litteraturbanken.se/#!/forfattare/KellgrenJH/titlar/SamladeSkrifter2/info Część 3, Utwory teatralne. 1941-1942. Libris 114765. http://litteraturbanken.se/#!/forfattare/KellgrenJH/titlar/SamladeSkrifter3/info Część 4, Pisa prozaiczne od początku publikacji &quot;Stockholms posten&quot; do roku 1784. 1940-1944. Libris 114766. http://litteraturbanken.se/#!/forfattare/KellgrenJH/titlar/SamladeSkrifter4/info Część 5, Pisa prozaiczne z lat 1785-1795, Tom 1, Pisa prozaiczne z lat 1785-1789; Rozproszone pisma prozaiczne z lat 1790-1795. 1945-1946. Libris 114772. http://litteraturbanken.se/#!/forfattare/KellgrenJH/titlar/SamladeS</p><h3>Jak pewne są te informacje?</h3><p>Osobowości epoki oświecenia są dobrze udokumentowane dzięki publikacjom parlamentarnym, listom i archiwom. Interpretacja ich ról często jest zabarwiona późniejszymi przekonaniami politycznymi.</p>",
  "relevans": {
    "b_kultur": 3,
    "pensionar": 3,
    "kultur": 5
  },
  "epok": "frihetstiden",
  "tid": "d. 1795",
  "kallage": "samtida",
  "sakerhet": "belagt",
  "konsensus": "samsyn",
  "flaggor": [],
  "tldr": "Johan Henric Kellgren był znanym szwedzkim pisarzem, poetą i redaktorem czasopism w XVIII wieku. Zyskał sławę dzięki swoim poezjom oraz jako pierwszy krytyk teatralny w Szwecji.",
  "lattlast": "<p>Johan Henric Kellgren urodził się w 1751 roku i poświęcił się literaturze, co obejmowało pisanie książek i wierszy. Rozpoczął współpracę z gazetą &quot;Stockholms-Posten&quot; w 1778 roku, stając się pierwszą osobą w Szwecji, która pisała recenzje spektakli teatralnych.</p><p>Kellgren zyskał dużą uwagę króla Gustawa III. Dzięki swojej pracy w dziedzinie kultury i literatury otrzymał od króla rentę oraz ważne stanowiska w bibliotece królewskiej i na dworze. Był również jednym z pierwszych członków Szwedzkiej Akademii, organizacji zajmującej się językiem szwedzkim.</p><p>Pisał różnorodne teksty, w tym wiersze o miłości i satyryczne utwory, które parodiują coś lub kogoś. Brał udział w znanych debatach z innymi pisarzami oraz pisał libretta do oper we współpracy z królem. Mimo że był bardzo ceniony, zmarł w 1795 roku na gruźlicę.</p>"
}