{
  "id": "hist-q350420",
  "typ": "historia",
  "titel": "Salomon August Andrée.",
  "datum": "",
  "kalla": "Wikipedia",
  "kalla_url": "https://sv.wikipedia.org/wiki/Salomon_August_Andrée",
  "taggar": [
    "svensk-historia",
    "historisk-person",
    "1800talet"
  ],
  "html": "<p>Salomon August Andrée, plus communément appelé S. A. Andrée, né le 18 octobre 1854 à Gränna et décédé en octobre 1897 sur l&#x27;île de Vitön (au nord-est des îles Svalbard), était un ingénieur de brevets, physicien et explorateur polaire suédois, connu pour l&#x27;expédition polaire d&#x27;Andrée, une tentative infructueuse de 1897 visant à atteindre le pôle Nord en ballon à hydrogène.</p><p>== Biographie == Andrée était le fils de Claes Georg Andrée, pharmacien, et de Jacobina (Mina) Gustafva, née Heurlin (fille du pasteur Elias Heurlin), décédée le 29 avril 1897. Il a été élève du lycée supérieur de Jönköping de 1863 à 1870 et étudiant régulier de l&#x27;Institut Technologique de 1871 à 1874. Andrée a travaillé comme dessinateur dans l&#x27;atelier mécanique Göranssons à Stockholm de 1874 à 1876, a effectué un voyage d&#x27;études en Angleterre et en Amérique en 1876, a été maître d&#x27;usine aux usines de Norrahammar et Spånhult de 1877 à 1878, a été associé de la société Andrée &amp; Möller et a travaillé à l&#x27;usine de Stillefors de 1878 à 1879. Il a été assistant en physique à l&#x27;École Royale Supérieure de Technologie de 1880 à 1882, ingénieur principal à l&#x27;Office des Brevets de 1884 à 1897 et professeur suppléant de physique expérimentale à l&#x27;École Technique de Stockholm de 1886 à 1889. Andrée a été membre du conseil municipal de Stockholm de 1891 à 1894 et de la Société Technologique Suédoise de 1872 à 1897. Il était également favorable au libre-échange et à l&#x27;égalité entre les sexes.</p><p>== L&#x27;expédition polaire d&#x27;Andrée ==</p><p>=== Les voyages en ballon et la tentative depuis les îles Svalbard ===</p><p>Andrée est devenu célèbre en Suède pour avoir réalisé le premier voyage en ballon de Suède à Finlande.  Cependant, il avait très peu d&#x27;expérience – seulement 40 heures – dans le domaine du vol en ballon avant de publier ses plans pour un voyage en ballon vers le pôle Nord. Depuis Göteborg, Andrée a effectué plusieurs vols en ballon, par exemple le 26 février 1894 à midi, lorsqu&#x27;il est parti du nouveau gazomètre près de Gullbergsvass et a atterri à trois kilomètres de la gare de Vara, et le 4 août depuis le même point de départ jusqu&#x27;à Trollhättan, en deux heures. Ses idées ont suscité l&#x27;enthousiasme du public et il a reçu un soutien financier principalement d&#x27;Alfred Nobel, Oscar II et Oscar Dickson.</p><p>Une première tentative pour mener à bien une expédition vers le pôle Nord a été réalisée en juin 1896 avec le ballon &quot;Örnen&quot;, accompagné de Nils Ekholm et du photographe Nils Strindberg. Les membres de l&#x27;expédition ont quitté le port de Göteborg depuis la nouvelle jetée à bord du bateau à vapeur &quot;Virgo&quot; à destination des îles Svalbard et de la côte nord-ouest du Danemark, et ils se sont embarqués au domicile de Pike dans le port de &quot;Virgo&quot; le 22 juin 1896, où le déchargement a eu lieu. Là, à 79 degrés 43 minutes de latitude Nord, l&#x27;équipe a commencé à construire le hangar du ballon avec l&#x27;aide de l&#x27;équipage du &quot;Virgo&quot;, dans des conditions météorologiques très défavorables. Le ballon était prêt et gonflé pour le départ pendant trois semaines, entre le 27 juillet et le 17 août, mais les faibles vents soufflant du sud étaient insuffisants pour permettre un voyage plus long vers le nord. Ainsi, le 17 août, il a été décidé de ranger le ballon et l&#x27;équipement technique et de retourner à Göteborg, car le risque d&#x27;une tentative de voyage vers le nord était trop élevé. De plus, les terres au-delà du 82e degré de latitude Nord n&#x27;étaient pas encore explorées. Le hangar du ballon, solidement sécurisé contre le vent et contenant une demi-réservoir d&#x27;hydrogène, a été laissé sur place pour être utilisé lors de futures expéditions. Le samedi 29 août 1896, le &quot;Virgo&quot;, dirigé par le capitaine Zachau, a pu accoster à la nouvelle jetée du port de Göteborg.</p><p>Ekholm a abandonné le projet en octobre 1896, estimant que c&#x27;était trop risqué. En particulier, les conditions météorologiques dans l&#x27;océan Arctique – notamment les vents – étaient insuffisamment étudiées. Il a été remplacé par l&#x27;ingénieur Knut Frænkel pour la prochaine tentative. Gustaf Wilhelm Emanuel Svedenborg a également été désigné comme remplaçant au cas où l&#x27;un des participants ne pourrait pas participer.</p><p>=== L&#x27;expédition Örnen === Le 11 juillet 1897, les vents du sud étaient favorables et Andrée, ainsi que ses compagnons Fraenkel et Strindberg, ont décollé à bord de la montgolfière &quot;Örnen&quot; en direction du pôle Nord. Presque immédiatement après le départ, des problèmes sont apparus : certaines parties des câbles d&#x27;ancrage inventés par Andrée (qui devaient servir à diriger et à contrôler la vitesse de la montgolfière, ainsi qu&#x27;à la lestrer légèrement pour atteindre l&#x27;altitude prévue) se sont détachées au niveau d&#x27;une jonction située plus bas. Cependant, Andrée a pu réparer cela grâce aux câbles de rechange qu&#x27;il avait emportés. De plus, les cinq câbles étaient légèrement mal positionnés, ce qui a fait pivoter la montgolfière d&#x27;un demi-tour après le décollage. Après un peu plus de deux jours de vol, l&#x27;expédition aérienne s&#x27;est terminée (les valves ont été ouvertes) car l&#x27;air humide a créé de la glace qui alourdissait la montgolfière. Ils ont ensuite entamé leur marche sur la banquise en direction de la base avancée située dans les îles Frances Joseph. Cependant, la banquise les a entraînés vers l&#x27;ouest, et ils ont donc modifié leur itinéraire en direction du Svalbard et de la base située à Sjuöya, au nord du Svalbard. Pendant trois mois, les trois hommes se sont battus sur la banquise qui dérivait de plus en plus vers le sud, avant de s&#x27;installer sur l&#x27;île de Vitön, où la plaque de glace a touché terre. Ils y sont décédés pour des raisons non établies : d&#x27;abord Strindberg, puis Andrée et Fraenkel.</p><p>=== Postérité === À l&#x27;exception d&#x27;un pigeon voyageur et de quelques bouées de sauvetage retrouvées, l&#x27;expédition n&#x27;a donné aucun signe de vie pendant 33 ans. Les restes des membres de l&#x27;expédition, ainsi que leurs outils et leurs journaux, ont été découverts en 1930 sur l&#x27;île de Vitön. Cet événement a suscité une immense médiation. Les journaux avaient été conservés de manière à ce que l&#x27;on puisse lire leur contenu.</p><h3>Comment pouvons-nous être sûrs de tout cela ?</h3><p>Les personnes du XIXe siècle sont très bien documentées (registres paroissiaux, journaux, lettres). L&#x27;incertitude concerne principalement la sélection et les perspectives : quelles histoires sont mises en avant.</p>",
  "relevans": {
    "b_transport": 3,
    "b_kultur": 3,
    "immaterialratt": 3,
    "flygresenar": 3
  },
  "epok": "1800talet",
  "tid": "d. 1897",
  "kallage": "samtida",
  "sakerhet": "belagt",
  "konsensus": "samsyn",
  "flaggor": [],
  "tldr": "S.A. Andrée était un inventeur et chercheur suédois qui est devenu célèbre pour sa tentative infructueuse d'atteindre le Pôle Nord en ballon en 1897. Lui et ses deux compagnons sont morts sur la glace, et leurs journaux n'ont été retrouvés que 33 ans plus tard.",
  "lattlast": "<p>S.A. Andrée était un ingénieur et physicien formé, qui a travaillé sur divers projets avant de devenir célèbre pour ses tentatives de vol. Il a été professeur et a travaillé à l&#x27;Office des brevets, l&#x27;organisme chargé de protéger les nouvelles inventions. Il a reçu le soutien de personnalités éminentes, dont Alfred Nobel, pour tenter d&#x27;atteindre le pôle Nord avec un ballon propulsé par de l&#x27;hydrogène.</p><p>Avant cette grande expédition, il a effectué plusieurs vols plus modestes en Suède. En 1897, il s&#x27;est lancé dans ce grand voyage accompagné de deux autres hommes. Le vol ne s&#x27;est pas déroulé comme prévu car de la glace s&#x27;est formée sur le ballon et ils ont été contraints d&#x27;atterrir. Ils ont dérivé avec les glaces pendant trois mois avant d&#x27;atteindre une île appelée Vitön, où les trois hommes sont finalement décédés.</p><p>Personne ne savait ce qui leur était arrivé jusqu&#x27;en 1930, lorsque leurs journaux et leurs outils ont été découverts sur l&#x27;île. Grâce à la bonne conservation des journaux, il a été possible de lire comment ils avaient vécu pendant leur absence. L&#x27;histoire de leur voyage est devenue une grande nouvelle dans les médias lors de la découverte de ces objets.</p>"
}