{
  "id": "hist-q1347396",
  "typ": "historia",
  "titel": "نيلز داكي.",
  "datum": "",
  "kalla": "Wikipedia",
  "kalla_url": "https://sv.wikipedia.org/wiki/Nils_Dacke",
  "taggar": [
    "svensk-historia",
    "historisk-person",
    "vasatiden"
  ],
  "html": "<p>كان نيلز داكي، المولود حوالي عام 1510 في منطقة فِيسْفِيَارْدَا الريفية في سمولاند، وتوفي في أغسطس عام 1543 في مرج أولاتوربيت بالقرب من فلاكا في تورساوس، مقاطعة كالمار، مزارعًا سمولانديًا وقائدًا للتمرد.</p><p>اشتهر نيلز داكي كقائد لثورة فلاحية في سمولاند، والتي تُعرف باسم &quot;حرب داكي&quot;. عارض نيلز داكي و followersه العديد من الأمور، بما في ذلك الضغط الضريبي في سمولاند، وإدخال المسيحية الإنجيلية اللوثرية في المنطقة، حيث قام الملك غوستاف فاسا بمصادرة الفضة الكنسية وغيرها من الممتلكات التي جمعها المزارعون السمولانديون على مر القرون - كل ذلك في سياق جهود الملك لتعزيز سلطته المركزية في ستوكهولم.</p><p>انتهت الثورة بهزيمة. هُزم رجال داكي لأن قادة التمرد افتقروا إلى الموارد الاقتصادية والنفوذ السياسي الذي كان يتمتع به غوستاف فاسا، وقُتل داكي على يد رجال المسؤول الحكومي.</p><p>== السيرة الذاتية == من المحتمل أن يكون نيلز داكي قد ولد حوالي عام 1510 في منطقة فِيسْفِيَارْدَا الريفية في سمولاند. أول ذكر لنيلز داكي في التاريخ السويدي يعود إلى عام 1536، عندما يُقال إنه قتل مسؤولًا حكوميًا في سلسلة من الاضطرابات الصغيرة في سمولاند. في ذلك الوقت، يُعتقد أن داكي كان في أوائل الثلاثينيات من عمره ولديه على الأقل ابن واحد. الاسم الذي أطلق على ابنه غير معروف. بعد ذلك، فر من العدالة لفترة طويلة، قبل أن يسلم نفسه للمحكمة حيث حُكم عليه بدفع غرامة قدرها 200 مارك، وهو مبلغ كبير جدًا في ذلك الوقت. بمساعدة أقاربه في قريته في منطقة سودرا موريه، تمكن من جمع المال. ثم استقر في مزرعة جديدة بجوار نهر ليكبي بالقرب من حدود بليكينج.</p><p>== حرب داكي ==</p><p>بعد بضع سنوات، ظهر اسم دَاكِه مرة أخرى في التاريخ. هذه المرة، كقائد لمجموعة من الفلاحين في المنطقة الذين قرروا القتال ضد تجاوزات المسؤول المحلي تجاه الفلاحين في المنطقة (وفقًا للمؤرخ لارس أولوف لارسن، فإن هذا الهجوم الأول يحمل بوضوح سمات الانتقام). بعد شهرين تقريبًا، وجد دَاكِه نفسه في موقع قوة لم يكن يتوقعه، حيث كان قائدًا للفلاحين في منطقة سمولاند. بعد إبرام اتفاق سلام مع غوستاف فاسا في 8 نوفمبر 1542، وبدلًا من التوجه إلى ستوكهولم بقواته، يبدو أن دَاكِه حاول تحقيق شعار الانتفاضة، وهو &quot;القديم والعتيق&quot;، من خلال إعادة فرض التجارة الحدودية مع الدنمارك بصفتها حاكمًا لمنطقة كرونوبيرغ، واستعادة الطقوس الدينية ما قبل الإصلاح في الكنائس، وما إلى ذلك.</p><p>في رسالة من الملك إلى العامة، تم وصف قائمة &quot;الجرائم&quot; المزعومة التي ارتكبها دَاكِه. لقد عاش &quot;ليس كمسلم، بل أسوأ من اليهود أو الوثنيين&quot;:</p><p>في ربيع عام 1543، هاجمت قوات الملك مرة أخرى، في انتهاك لاتفاق وقف إطلاق النار المتفق عليه، وحققت نصرًا ساحقًا بعد أن تعلمت كيفية التعامل مع تكتيكات الفلاحين. وفقًا للتقاليد، أصيب نيلس دَاكِه بجروح خطيرة. فقد ساقيه خلال المعركة الحاسمة على الجليد فوق بحيرة هجورتن في منطقة فيرسوم. ومع ذلك، تمكن رجاله من إخراجه إلى بر الأمان، وظل بعيدًا عن قوات الملك لمدة شهرين. في النهاية، قُتل دَاكِه في أغسطس 1543 في مرج أولاتوربت بالقرب من المزرعة التي كان يستخدمها في بداية الانتفاضة، بالقرب من فلاكا في تورساوس، وهي الآن منطقة غولابو. كل ذلك يقع في منطقة سودرا موريه، مقاطعة كالمار، بالقرب من الحدود السابقة للمملكة مع بليكنغه، الدنمارك. وقد قُتل بإطلاق النار عليه من قبل رجال المسؤول، الذين يُقال إنهم كانوا بقيادة أحد ضباطه السابقين. تم وضع نصب تذكاري في هذا المكان. بعد الانتفاضة، تم دفنه بعد وفاته ونقل جثمانه إلى كالمار، بما في ذلك رأسه الذي وُضع على عمود في منطقة الإعدام. عندما وردت أنباء عن وفاة زعيم الانتفاضة، كتب غوستاف فاسا الرسالة التالية إلى الحاكم في مقاطعة كالمار:</p><p>وفقًا لمصادر غير مؤكدة، أمر الملك غوستاف فاسا بتعذيب ابن داكي حتى الموت في زنزانة سجن، خوفًا من القيمة الرمزية التي يمثلها الابن وإمكانية حدوث انتفاضة جديدة.</p><p>تشير إحدى الأساطير إلى أن الشخص الذي قُتل لم يكن داكي نفسه، بل شخص يشبهه وقد أصيب أيضًا بإطلاق نار في كلا الفخذين. يُزعم أن داكي الحقيقي فرّ إلى ألمانيا وعاد إلى السويد خلال فترة حكم يوهان الثالث، حيث تم خداعه وأسرِه ثم استُعرض في شوارع ستوكهولم وهو يرتدي تاجًا نحاسيًا على رأسه. بعد ذلك، يُقال أنه أُودِع مستشفى وتوفي خلال عام الطاعون عام 1580. ومن بين آخرين، ذكر بير براهي أن الأمر انكشف لاحقًا بأن الرجل الذي تم تعذيبه في كالمار لم يكن داكي الحقيقي.</p><p>== الإرث ==</p><p>في المناطق التي وقعت فيها حرب داكي، وخاصة في جنوب شرق سمولاند، لا يزال اسم نيلز داكي معروفًا جيدًا. أُقيمت تماثيل تكريمًا له في أماكن مختلفة في منطقة سوردا موريه، وفي فيرسيروم - حيث دارت معركة حاسمة خلال حرب داكي في أسبوع عيد الفصح عام 1543 - وفي أماكن أخرى. كما سُميت شوارع وشركات وأندية رياضية (مثل نادي سبيدواي &quot;داكارنا&quot;) ومدارس وفرق كشفية ومنظمات أخرى، بالإضافة إلى العديد من المؤسسات، باسمه. في مزرعته &quot;سودرا ليندون&quot; في منطقة فسيفردا، أُقيمت شاحنة تذكارية له عام 1985. تحمل الشاحنة النقش التالي: &quot;هنا، في مزرعة الملكية &quot;س ليندون&quot;، عاش نيلز داكي حتى قام بإطلاق النار على الحاكم &quot;إنجي آندرسون&quot; الذي كان قاسياً وغير صبور في الربيع عام 1536. لقد حافظ أحفاده الذين عاشوا في المزرعة على التقاليد الشفوية. أُقيمت الشاحنة عام 1985 بواسطة هارالد سفينسون.&quot; وفي ستورا فلاكا، توجد شاحنة تحمل الكلمات &quot;نيلز د...&quot;.</p><h3>ما مدى يقيننا من هذه المعلومات؟</h3><p>بدءًا من عصر فاسا، تم توثيق الأشخاص بشكل جيد في الأرشيف. تكمن الشكوك في تفسير الأحداث وتصورات الأجيال اللاحقة - وخاصة وأن السلطة نفسها شاركت في تشكيل كتابتها الخاصة للتاريخ.</p>",
  "epok": "vasatiden",
  "tid": "d. 1543",
  "kallage": "samtida",
  "sakerhet": "belagt",
  "konsensus": "samsyn",
  "flaggor": [],
  "tldr": "كان نيلز داكي مزارعًا من منطقة سمولاند، وقاد تمردًا في القرن السادس عشر ضد الضرائب الباهظة والتغييرات التي أحدثها الملك غوستاف فاسا في الكنيسة. أصبح رمزًا للمقاومة ضد سلطة الملك، لكنه قُتل في القتال بعد أن هُزم أمام جيش الملك.",
  "lattlast": "<p>كان نيلز داكي مزارعًا اشتهر بكونه زعيمًا لتمرد يُعرف باسم &quot;حرب داكي&quot;. لقد قاتم هو وأتباعه ضد الضرائب المرتفعة التي فرضها الملك غوستاف فاسا، وضد التغييرات التي طالت الكنيسة من العقيدة الكاثوليكية القديمة إلى التعاليم اللوثرية الجديدة. كما أراد استعادة التجارة مع الدنمارك والحفاظ على العادات والتقاليد القديمة.</p><p>كانت هذه الثورة عنيفة، وأصبح داكي رمزًا لنضال الفلاحين ضد سلطة الملك المتزايدة في السويد. خلال المعارك التي اندلعت في أربعينيات القرن السادس عشر، أصيب بجروح خطيرة، لكنه تمكن من الاختباء لفترة قبل أن يموت في النهاية متأثرًا بإصابته بعد أن طارده رجال الملك. هناك أيضًا قصص تتحدث عن أن ابنه عوقب بشدة بسبب كونه ابن داكي.</p><p>حتى اليوم، لا يزال اسم نيلز داكي معروفًا في منطقة سمولاند. العديد من الأماكن، مثل الشوارع والمدارس والجمعيات، تحمل اسمه. توجد أيضًا نصب تذكارية في الأماكن التي عاش فيها وفي المواقع التي دارت فيها أهم المعارك.</p>"
}