{
  "id": "hist-q553292",
  "typ": "historia",
  "titel": "یاکوب د لا گاردیه",
  "datum": "",
  "kalla": "Wikipedia",
  "kalla_url": "https://sv.wikipedia.org/wiki/Jakob_De_la_Gardie",
  "taggar": [
    "svensk-historia",
    "historisk-person",
    "stormaktstiden"
  ],
  "html": "<p>لطفاً این متن را با ژاکوب پانتوسون د لا گاردی (Jacob Pontusson De la Gardie)، که یک سیاستمدار و رئیس منطقه بود (1768-1842)، اشتباه نکنید.</p><p>ژاکوب پانتوسون د لا گاردی، متولد 20 ژوئن 1583 در ریوال (Reval)، درگذشته 12 اوت 1652 در استکهلم، یک فرمانده نظامی سوئدی، فیلد مارشال، عضو شورای سلطنتی سوئد و از تاریخ 10 می 1615، کنت لکشو (Läckö) بود. ژاکوب د لا گاردی نقش مهمی در عملیات نظامی &quot;د لا گاردی&quot; و همچنین در جنگ اینگرمانلند داشت.</p><p>== بیوگرافی == یاکوب د لا گاردی در ریوال (شهر فعلی تالین) در استونی به دنیا آمد. او پسر پونطوس د لا گاردی و همسرش سوفیا یوهانس‌دوتتر (گیلن هیلم) بود که دختر نامشروع یوهان سوم بود. مادرش هنگام تولد یاکوب، که سومین فرزند خانواده بود، در رحِم جان باخت. پدرش در سال 1585 در نزدیکی ناروا غرق شد. پس از آن، یاکوب خواهرش بریتا و برادرش یوهان را داشت.</p><p>د لا گاردی از سنین پایین وارد خدمت نظامی شد و در سن 18 سالگی به مقام سرتیپ یک هنگ شمالی منصوب گردید. او در دفاع از ولمار در برابر لهستانی‌ها شرکت کرد، اما اسیر شد. او تا سال 1606 آزاد نشد و سپس به هلند رفت، جایی که تحت فرماندهی موریتس اورانژ، هنر جنگی هلندی را فرا گرفت.</p><p>پس از بازگشت به سوئد در سال 1609، او به مقام ژنرال ارشد منصوب شد و مسئولیت نیروهایی را بر عهده گرفت که کارل نهم برای حمایت از تزار واسیل چهارم روسیه فرستاده بود، که به &quot;کمپین د لا گاردی&quot; معروف است. این ماموریت دشوار بود، اما با همکاری میخائیل اسکوپین-شویسکی، او موفق شد تا به مسکو برسد و در ماه مارس 1610 شهر را تصرف کند. احتمالاً در این زمان، او اولین و آخرین سوئدی بود که از مقبره گوستاو اریکسون واسا، پسر اریش چهاردهم و شاهزاده وارث سابق سوئد، که در نزدیکی مسکو در شهر کاچین دفن شده بود، بازدید کرد.</p><p>با شروع دخالت سیگیسموند در امور روسیه، د لا گاردی به همراه نیروهای تقویتی از سوئد و یک نیروی روسی، علیه لهستانی‌ها وارد عمل شد. اختلافات بر سر حقوق سربازان باعث نارضایتی در میان نیروهای مزدور شد. در 24 ژوئن 1610، هنگامی که بین ارتش سوئدی-روسی و لهستانی به رهبری استانیسلاو زولکوفسکی در کلوشینو نبردی رخ داد، سربازان پیاده‌نظام خارجی د لا گاردی از شرکت در آن امتناع کردند. روس‌ها فرار کردند و د لا گاردی مجبور شد با زولکوفسکی قراردادی ببندد مبنی بر عدم حمایت بیشتر از تزار واسیل چهارم، اما او بعدها این قرارداد را رد کرد.</p><p>او با 400 سرباز سوئدی و فنلاندی، که باقی‌مانده نیروهایش بودند، با دشواری فراوان به مرز سوئد بازگشت. او نیروهای بیشتری دریافت کرد، اما همچنین در مذاکرات با عناصر مخالف لهستانی‌ها در روسیه شرکت داشت. علاوه بر قلعه ککسهولم، که از قبل در سال 1609 به عنوان پاداش برای حمایت سوئدی‌ها وعده داده شده بود، اما تحویل داده نشده بود و در مارس 1611 تصرف شد، د لا گاردی خواستار قلعه‌های نووتگورود و استارا لادوگا نیز شد. روس‌ها با این درخواست موافقت نکردند، اما در عوض در ژوئن 1611 گوستاو آدولف را به عنوان تزار روسیه انتخاب کردند. د لا گاردی این موضوع را به پادشاه ارجاع داد، اما برای ایجاد وثیقه برای مطالبات سوئد، در 16 جولای 1611 شهر مهم نووگورود را تصرف کرد. این شهر سپس در یک پیمان، کارل نهم را به عنوان حامی خود پذیرفت و با امید به پیوستن سایر مناطق روسیه، گوستاو آدولف یا کارل فیلیپ را به عنوان تزار انتخاب کرد.</p><p>پس از اینکه گوستاو آدولف پادشاه سوئد شد، کارل فیلیپ به عنوان تنها نامزد شناخته می‌شد که می‌توانست از حمایت روسیه برخوردار باشد. با این حال، کاندیداتوری او توسط شاهدزاده کریستینا از هولشتاین-گوتورپ مورد مخالفت قرار گرفت و سفر او به روسیه به تعویق افتاد. در همین زمان، میخائیل رومانوف در سال 1613 به عنوان تزار انتخاب شد. د لا گاردی که از موضع دولت سوئد ناراضی بود، سعی کرد تا حد امکان کنترل را حفظ کند، اما شهرهای بیشتری شورش کردند و از رومانوف حمایت کردند. با این حال، با استفاده از نیروهایی که در شهر مستقر بودند، موفق شدند از شورش نووگورود جلوگیری کنند.</p><p>در پاییز سال 1614، د لا گاردی همراه با گوستاو دوم آدولف، که یک سال در این کمپین شرکت کرده بود تا هنر جنگ را بیاموزد، به سوئد بازگشت. او در سال 1615 همراه با پادشاه و در رهبری محاصره پسکوف شرکت کرد، اما این تلاش ناموفق بود. موفقیت‌های حاصل شده در پیمان استولبووا، که د لا گاردی یکی از نمایندگان آن بود، تا حد زیادی به دلیل تصرفات د لا گاردی بود. او در سال 1613 به مقام عضو شورای سلطنتی منصوب شد و در سال 1615 به مقام اشراف ارتقا یافت و لکشو به عنوان املاک اشرافی به او اعطا شد. این تنها عنوان اشرافی بود که گوستاو دوم در طول بیست و یک سال حکومت خود اعطا کرد. در 24 ژوئن 1618، د لا گاردی با اِبا براهه ازدواج کرد. زوج در اقامتگاه سوانا در پارکی از منطقه وستمانلند ساکن شدند. او در سال 1619 به عنوان فرماندار استونی منصوب شد، در سال 1621 در تصرف ریگا شرکت کرد و سپس به مقام ژنرال فرمانداری لیوولند ارتقا یافت. در غیاب پادشاه، او فرماندهی نیروهای مستقر در استان‌های بالتیک را بر عهده داشت و اغلب مذاکرات با لهستانی‌ها را رهبری می‌کرد. در سال 1625، او دورپات را تصرف کرد، اما در غیر این صورت دستاوردهای نظامی قابل توجهی نداشت. در عوض، اقدامات او اغلب به عنوان عامل شکست در نبرد والوف در سال 1626 تلقی می‌شد. گوستاو دوم آدولف در سال 1628، او را &quot;کمی کند و دیر عمل کننده&quot; توصیف کرد.</p><h3>چطور می‌توانیم از این موضوع مطمئن باشیم؟</h3><p>شخصیت‌های دوران امپراتوری‌ها، به طور کامل در بایگانی‌ها و اسناد هم‌عصر ثبت شده‌اند. بیشتر اطلاعات مربوط به هویت آن‌ها و کارهایی که انجام داده‌اند، مستند است؛ ابهام عمدتاً در تفسیر و انگیزه‌ها نهفته است.</p>",
  "epok": "stormaktstiden",
  "tid": "d. 1652",
  "kallage": "samtida",
  "sakerhet": "belagt",
  "konsensus": "samsyn",
  "flaggor": [],
  "tldr": "این متن درباره یاکوب د لا گاردی است، یک فرمانده نظامی برجسته سوئدی در قرن هفدهم که در جنگ‌های مهمی در روسیه و استونی رهبری داشت.",
  "lattlast": "<p>یاکوب د لا گاردی، یکی از فرماندهان ارشد ارتش سوئد بود. او در قرن پانزدهم متولد شد و به دلیل رهبری نیروهای سوئدی در جنگ‌هایی علیه لهستانی‌ها و نیروهای روسی مشهور گردید. در دوران رهبری خود، موفق شد کنترل چندین شهر مهم را به دست گیرد، از جمله نووگورود، که این امر باعث افزایش قدرت سوئد در آن منطقه شد.</p><p>او شخصیتی بسیار برجسته بود که در سال 1615 به عنوان &quot;گریف&quot; (معادل اشراف) لکشو منصوب گردید. این بدان معناست که او یک مقام عالی رتبه دریافت کرد و زمین‌هایی را به عنوان پاداش برای خدماتش تصاحب نمود. همچنین، او به عنوان فرماندار خدمت می‌کرد، یعنی بر مناطق استونی و لیوونی (بخشی از کشورهای امروزی حوزه بالټیک) به نمایندگی از پادشاه سوئد حکومت می‌کرد.</p><p>با وجود اینکه او یک رهبر ماهر بود، گاهی اوقات مورد انتقاد شاه گوستاو دوم آدوف قرار می‌گرفت. شاه معتقد بود که د لا گاردی ممکن است در تصمیم‌گیری‌هایش کمی کند عمل کند و همیشه به اندازه کافی سریع نبود، به‌ویژه در زمان جنگ.</p>"
}