{
  "id": "hist-q320977",
  "typ": "historia",
  "titel": "Knut Eriksson.",
  "datum": "",
  "kalla": "Wikipedia",
  "kalla_url": "https://sv.wikipedia.org/wiki/Knut_Eriksson",
  "taggar": [
    "svensk-historia",
    "historisk-person",
    "medeltid"
  ],
  "html": "<p>Knut Eriksson, nacido a finales del siglo XII (probablemente en la década de 1140), y fallecido en 1195 o 1196, fue rey de Suecia desde 1167, hijo de Erik el Santo y Kristina Björnsdotter de Dinamarca.</p><p>Knut Eriksson tomó el poder inicialmente asesinando a Karl Sverkersson (en un ataque en Visingsö en 1167). Posteriormente, en 1172/1173, derrotó y mató a los medio hermanos de Karl Sverkersson, Kol y Burislev, quienes se habían proclamado reyes y controlaban Östergötland. En 1173 fue reconocido como rey y gobernó durante 23 años. Una de sus acciones más importantes fue su esfuerzo por lograr la canonización de su padre, Erik el Santo. Sin embargo, este objetivo resultó imposible debido a que el Papa Alejandro III estaba muy molesto porque Stefan, el arzobispo de Uppsala, se había visto obligado a huir para salvar su vida cuando Knut Eriksson tomó el poder. Otra importante contribución de Knut Eriksson fue la reanudación de la acuñación de monedas, que inexplicablemente había estado suspendida durante 150 años.</p><p>Knut estaba casado con una mujer sueca, cuya familia solo se sabe con certeza que tenía un hermano llamado Knut. Basándose en supuestas interpretaciones erróneas de fuentes históricas, a ella se le atribuye el nombre de Cecilia. A través de una bula papal de 1193, conservada en copia, se sabe que durante una enfermedad grave, hizo un voto de castidad y entró en un monasterio después de recuperarse. Posteriormente, el rey Knut solicitó al Papa que la liberara de este voto.</p><p>== Biografía == Tras la muerte de su padre, Erik el Santo, alrededor de 1160, Knut fue derrotado por sus oponentes y se vio obligado a huir del reino. Según una crónica mucho más tardía (del siglo XIV), permaneció tres años en Noruega. Sin embargo, esta información no aparece en las crónicas reales noruegas y probablemente se debe a que el autor de la crónica confundió a Knut con su hijo, Erik. Knut regresó en 1167 y, según la lista real de la Ley de Västergötland, asesinó al rey Karl Sverkersson en Visingsö. Posteriormente, tuvo que luchar contra los familiares de Karl Sverkersson, Kol y Burislev, quienes reclamaban el trono con el apoyo de Dinamarca. Después de derrotar y matar a sus competidores (aproximadamente entre 1172 y 1173), Knut gobernó Suecia sin oposición durante veintitrés años (según la lista real de la Ley de Västergötland). Durante el reinado de Knut Eriksson, se originó el primer tratado comercial sueco conocido con otro reino: en este caso, Lübeck. Fue firmado por su *jarl* (duque) Birger Brosa entre Knut Eriksson y el duque Enrique el León de Sajonia. Knut también estableció relaciones diplomáticas con Inglaterra alrededor de 1185 y, en ese contexto, recibió una armadura como regalo del rey inglés Enrique II. Según la saga de Sverre, Knut (y los demás reyes nórdicos) recibieron en 1195 una carta solicitando asistencia militar del emperador bizantino Alejo III Ángelo. Knut también mantuvo buenas relaciones con el rey noruego Sverre Sigurdsson, quien se casó con la hermana de Knut, Margarita, en 1185, pero las relaciones con los reyes daneses fueron más tensas. Según registros medievales, Sigtuna fue atacada y quemada por piratas en 1187 durante el reinado de Knut, según la Crónica de Karelia, pero las excavaciones arqueológicas han demostrado que no existe ninguna capa de fuego en Sigtuna que pueda relacionarse con esta información. Según las mismas fuentes, el arzobispo Johannes fue asesinado en ese mismo evento cerca del castillo de Almarestäket. Los documentos reales suecos más antiguos conservados fueron emitidos por Knut, y él también fue uno de los primeros, después de Karl Sverkersson, en llamarse rey de Svear (suecos) y Götar (habitants de Götaland). De los nueve documentos originales conservados, ocho pertenecen al monasterio de Viby cerca de Sigtuna. También hubo una acuñación extensa durante el reinado de Knut, donde al menos tres monedas muestran al rey con un escudo adornado con barras. Estas podrían haber sido la inspiración para el escudo representado en el sudario de Holmger Knutsson. Knut murió de causas naturales en 1195 (o 1196) y fue enterrado en la iglesia del monasterio de Varnhem, donde varios siglos después Magnus Gabriel De la Gardie hizo colocar una lápida sobre su tumba. En general, se puede considerar que el largo reinado de Knut fue un período en el que el estado sueco comenzó a establecerse seriamente siguiendo un modelo continental, con una administración central escrita y relaciones diplomáticas documentadas con otros reinos. Sin embargo, las fuentes no proporcionan información sobre cómo se debe distribuir el mérito de esto entre el rey Knut y su *jarl* Birger Brosa. Fue sucedido como rey por Sverker el joven, hijo de su predecesor. Hijos:</p><p>Tres hijos, cuyos nombres se desconocen, murieron en la batalla de Älgarås en 1205. Erik, rey sueco de 1208 a 1216. Sigrid, casada con Magnus Broka.</p><p>== Galería de imágenes ==</p><p>== Véase también == La familia real de Erik.</p><p>== Fuentes ==</p><p>Este artículo está basado completamente o parcialmente en material de la &quot;Nordisk familjebok&quot;, Knut, del 24 de junio de 1911.</p><h3>¿Qué tan seguros estamos de esto?</h3><p>Para las personas de la Edad Media, a menudo existen fuentes escritas contemporáneas (cartas, crónicas, documentos eclesiásticos), por lo que los aspectos más importantes suelen estar documentados. Sin embargo, estas fuentes fueron escritas principalmente por la iglesia y los gobernantes, y su conservación es desigual, lo que distorsiona y limita la imagen.</p>",
  "relevans": {
    "b_bygg": 3
  },
  "epok": "medeltid",
  "tid": "d. 1196",
  "kallage": "samtida",
  "sakerhet": "trolig",
  "konsensus": "samsyn",
  "flaggor": [
    "tidsavstand"
  ],
  "tldr": "Knut Eriksson fue un rey sueco que gobernó el país durante 23 años en el siglo XII. Es conocido por haber sido uno de los primeros en utilizar documentos escritos y acuñar monedas, lo que contribuyó a fortalecer el poder del estado sueco.",
  "lattlast": "<p>En el año 1167, Knut Eriksson se convirtió en rey de Suecia tras un período de conflictos y guerras. Durante sus veintitrés años de reinado, realizó importantes contribuciones al país, como la reanudación de la acuñación de monedas y la creación de los primeros acuerdos escritos con otros países. También fue el primer rey en mucho tiempo que utilizó el título de &quot;Rey de Svear y Götar&quot;.</p><p>Durante el reinado de Knut, Suecia comenzó a gobernarse más similarmente a otros países europeos, utilizando documentos escritos para gestionar los asuntos del estado. Esto hizo que la autoridad sobre el país fuera más clara y organizada. También mantuvo buenas relaciones con otros reyes, como los de Inglaterra y Noruega.</p><p>Knut era hijo de Erik el Santo e intentó conseguir que su padre fuera reconocido como santo por la Iglesia, pero no lo logró porque el Papa estaba en desacuerdo con la forma en que se había tomado el poder. Knut murió alrededor del año 1195 o 1196 y fue enterrado en la iglesia-monasterio de Varnhem.</p>"
}