{
  "id": "hist-q350420",
  "typ": "historia",
  "titel": "Salomon August Andrée",
  "datum": "",
  "kalla": "Wikipedia",
  "kalla_url": "https://sv.wikipedia.org/wiki/Salomon_August_Andrée",
  "taggar": [
    "svensk-historia",
    "historisk-person",
    "1800talet"
  ],
  "html": "<p>Salomon August Andrée, jota elämäns aikana usein kutsutti vain S. A. Andréeksi, syntyi 18. lokakuuta 1854 Grännassa ja kuoli lokakuussa 1897 Vitön saarella (Spetsbergenin koillispuolella). Hän oli ruotsalainen patenttiteknikko, fyysikko ja naparetkeilijä, joka tunnetaan Andreen naparetkestä, epäonnistuneesta yrityksestä saavuttaa Pohjoisnapa vuonna 1897 vetypallolla.</p><p>== Elämäkerta == Andrée oli apteekkari Claes Georg Andréen ja Jacobina (Mina) Gustafvan (syntyjään Heurlin, prosti Elias Heurlinin tytär, kuollut 29. huhtikuuta 1897) poika. Hän opiskeli Jönköpingin yleisessä oppilaitoksessa vuosina 1863–1870 ja Teknillisessä instituutissa vuosina 1871–1874. Andrée työskenteli piirtäjänä Göranssonin mekaanisessa tehtaassa Tukholmassa vuosina 1874–1876, suoritti opintomatkan Englantiin ja Amerikkaan vuonna 1876, toimi mestarina Norrahammarin tehtaalla ja Spånhultin mekaanisessa tehtaassa vuosina 1877–1878, oli osakas yrityksessä Andrée &amp; Möller ja työskenteli Stilleforsin tehtaalla vuosina 1878–1879. Hän toimi fysiikan assistenttina Kuninkaallisessa teknillisessä korkeakoulussa vuosina 1880–1882, patenttiviraston pääinsinöörinä vuosina 1884–1897 sekä kokeellisen fysiikan yliopettajana Tukholman Teknillisessä koulussa vuosina 1886–1889. Andrée oli Tukholman kaupunginhallituksen jäsen vuosina 1891–1894 ja Svenska Teknologföreningenin jäsen vuosina 1872–1897. Hän kannatti vapaata kauppaa ja sukupuolten välistä tasa-arvoa.</p><p>== Andreen naparetki ==</p><p>=== Ilmapalloilut ja yritys Spitsbergeniltä === Andrée tuli tunnetuksi Ruotsissa tekemällä ensimmäisen ilmapallomatkan Ruotsista Suomeen. Muuten hänellä oli hyvin vähän kokemusta – vain 40 tuntia – ilmapallolennosta, ennen kuin hän julkaisi suunnitelmansa ilmapallomatkalle Pohjoisnavalle. Andrée lensi useita kertoja ilmapallolla Göteborgista, esimerkiksi 26. helmikuuta 1894 keskipäivällä, jolloin hän lähti Nya gasverket -tehtaalta Gullbergsvassissa ja laskeutui kolme kilometriä Vara-rautatieaseman etäisyydelle, sekä 4. elokuuta samasta lähtöpisteestä Trollhättaniin kahdessa tunnissa. Hänen ideansa herättivät innostusta yleisön keskuudessa, ja hän sai taloudellista tukea pääasiassa Alfred Nobelilta, Oscar II:lta ja Oscar Dicksonilta.</p><p>Ensimmäinen yritys Pohjoisnavalle suuntautuvalle retkelle tehtiin kesäkuussa 1896 ilmapallolla nimeltä Örnen yhdessä Nils Ekholmin ja valokuvaaja Nils Strindbergin kanssa. Retkikunnan jäsenet lähtivät aluksella &quot;Virgo&quot; Göteborgin satamasta Nya kajen -laiturilta kohti Spitsbergeniä ja Tanskanrannikon luoteisosia, ja he nousivat alukseen Pikes husissa sijaitsevalla laiturilla 22. kesäkuuta 1896, jossa lastaus tapahtui. Siellä, missä he olivat, 79 astetta pohjoista leveyttä, he aloittivat ilmapallohallin rakentamisen &quot;Virgon&quot; miehistön avulla erittäin huonoissa sääolosuhteissa. Ilmapallo oli valmis ja täytetty lähtöä varten kolmen viikon ajan, 27. heinäkuuta – 17. elokuuta välillä, mutta etelästä puhaltavat tuulet olivat liian heikkoja hyödynnettäväksi pidemmälle matkalle pohjoiseen. Siksi 17. elokuuta päätettiin pakata ilmapallo ja tekninen laitteisto ja palata takaisin Göteborgiin, koska pohjoiseen suuntautuvaan matkaan liittyi liian suuri riski. Myös alueen, joka ulottui 82 asteen pohjoiselle leveysasteelle, maasto oli kartoittamatta. Ilmapallohalli, joka oli hyvin suojattu tuulelta ja jossa oli puolet vetyä, jätettiin paikalle, jotta sitä voitaisiin käyttää tulevissa retkissä. Lauantaina 29. elokuuta 1896 alus &quot;Virgo&quot;, jonka kapteeni Zachau johti, saattoi kiinnittyä Nya kajen -laituriin Göteborgin satamassa.</p><p>Ekholm jätti projektin kesäkuussa 1896, koska hän katsoi sen olevan liian riskialtista. Yksi syy oli se, että Pohjoisjäämeren sääolosuhteet – erityisesti tuulet – olivat vielä liian vähän tutkittuja. Hänet korvattiin seuraavaa yritystä varten insinööri Knut Frænkelillä. Gustaf Wilhelm Emanuel Svedenborg hyväksyttiin myös varalle, jos joku osallistujista ei voisi osallistua.</p><p>=== Örnen-retkikunta ===</p><ol><li>heinäkuuta 1897 etelätuuli oli sopiva, ja Andrée sekä hänen kumppaninsa Fraenkel ja Strindberg nousivat vetypallolla nimeltään Örnen kohti Pohjoista navaa. Jo heti alussa ongelmia ilmeni, kun osa Andréen kehittämistä hinausköysistä (joita oli tarkoitus käyttää pallon ohjaamiseen, sen nopeuden rajoittamiseen ja painon lisäämiseen suunnitellun korkeuden saavuttamiseksi) irtautui liitoskohdasta alhaalla. André kuitenkin pystyi korjaamaan nämä, koska hänellä oli varaosat mukanaan. Lisäksi viisi hinausköyttä olivat hieman väärässä paikassa, minkä vuoksi pallo kääntyi puoli kierrosta heti nousun jälkeen. Runsas kahden vuorokauden lento päättyi, kun pallon venttiilit avattiin, koska kostea ilma aiheutti jään muodostumista, mikä painoi palloa alas. He aloittivat sitten vaelluksensa jäätiköllä itään kohti varastoa Frans Josefs Land -alueella. Jää kuitenkin ajautui heitä länteen, ja reitti muutettiin kohti Svalbardia ja varastoa Sjuöya-saarella pohjoisessa Svalbardissa. Kolmen kuukauden ajan kolmikko taisteli jäätiköllä, joka liikkui yhä etelämpään, ennen kuin he perustivat leirin Vitön saarelle, jossa jäälaatta törmäsi maahan. Siellä he kuolivat tuntemattomista syistä: ensin Strindberg, sitten Andrée ja Fraenkel.</li></ol><p>=== Jälkimainingit ===</p><p>Yhden harakkaan ja muutamien löydettyjen kelluvien pelastuslautojen lisäksi retkikunnasta ei kuulunut mitään 33 vuoden ajan. Retkikunnan jäsenten jäännökset sekä heidän työkalunsa ja päiväkirjansa löydettiin vuonna 1930 Vitön saarelta. Tämä oli valtava uutistapahtuma. Päiväkirjat olivat säilyneet niin hyvin, että niitä pystyi lukemaan.</p><h3>Kuinka varmasti tiedämme tämän?</h3><p>1800-luvun henkilöistä on olemassa erittäin paljon dokumentaatiota (väestötietojärjestelmät, sanomalehdet, kirjeet). Epävarmuutta aiheuttaa pääasiassa valinta ja näkökulma – kenen tarina nostetaan esiin.</p>",
  "relevans": {
    "b_transport": 3,
    "b_kultur": 3,
    "immaterialratt": 3,
    "flygresenar": 3
  },
  "epok": "1800talet",
  "tid": "d. 1897",
  "kallage": "samtida",
  "sakerhet": "belagt",
  "konsensus": "samsyn",
  "flaggor": [],
  "tldr": "S.A. Andrée oli ruotsalainen keksijä ja tutkija, joka tuli tunnetuksi epäonnistuneesta yrityksestään saavuttaa Pohjoisnapa ilmalaivalla vuonna 1897. Hän ja hänen kaksi seuralaisensa kuolivat jään päälle, ja heidän päiväkirjansa löydettiin vasta 33 vuoden kuluttua.",
  "lattlast": "<p>S.A. Andrée oli koulutettu insinööri ja fyysikko, joka työskenteli monissa eri tehtävissä ennen kuin hänestä tuli tunnettu lentoyrityksistään. Hän toimi muun muassa opettajana ja työskenteli patenttivirastossa, joka on viranomainen, jonka tehtävänä on suojella uusia keksintöjä. Hän sai tukea tunnetuilta henkilöiltä, kuten Alfred Nobelilta, pyrkiessään saavuttamaan Pohjoisnapa vetykaasulla toimivalla ilmapallolla.</p><p>Ennen suurta yritystä hän teki useita pienempiä lentoja Ruotsissa. Vuonna 1897 hän lähti suurelle matkalle yhdessä kahden muun miehen kanssa. Lento ei sujunut suunnitelmien mukaan, koska ilmapalloon muodostui jäätä ja heidän oli pakko laskeutua maahan. He ajautuivat jään mukana kolmen kuukauden ajan, kunnes saapuivat Vitön-nimiselle saarelle, jossa kaikki kolme lopulta menehtyivät.</p><p>Kenenkään ei ollut tietoa siitä, mitä heille oli tapahtunut, ennen kuin vuonna 1930 heidän päiväkirjansa ja työkalunsa löydettiin saarelta. Koska päiväkirjat olivat hyvin säilyneet, niistä pystyi lukemaan, millaista heillä oli ollut aikana, jolloin he olivat kadonneina. Heidän matkastaan kertova tarina tuli suureksi uutiseksi mediassa, kun löydöt tehtiin.</p>"
}